circkit/__init__.py
circkit/arithmetic.py
circkit/array.py
circkit/boolean.py
circkit/circuit.py
circkit/const_manager.py
circkit/location.py
circkit/node.py
circkit/node_info.py
circkit/operation.py
circkit/param.py
circkit/bitwise/__init__.py
circkit/bitwise/circuit.py
circkit/bitwise/const_manager.py
circkit/bitwise/ring.py
circkit/transformers/__init__.py
circkit/transformers/core.py
circkit/transformers/isw.py
circkit/utils/__init__.py
tests/__init__.py
tests/test_arithmetic_field.py
tests/test_arithmetic_number.py
tests/test_bitslicing_aes.py
tests/test_bitwise.py
tests/test_boolean.py
tests/test_builtin_circuit.py
tests/test_isw_transformer.py
tests/test_madd_mmul.py
tests/test_maddc_mmulc.py
tests/test_quadratic_masking.py
tests/test_simon_cipher.py
tests/test_speck_cipher.py
circkit-0.1.1.dist-info/LICENSE
circkit-0.1.1.dist-info/METADATA
circkit-0.1.1.dist-info/WHEEL
circkit-0.1.1.dist-info/top_level.txt
circkit-0.1.1.dist-info/RECORD
