Metadata-Version: 2.1
Name: circkit
Version: 0.1.1
Summary: A circuit toolkit mainly for cryptographic usage.
Home-page: https://github.com/CryptoExperts/circkit.git
Author: CryptoExperts
Author-email: contact@cryptoexperts.com
License: MIT
Classifier: Programming Language :: Python :: 3
Classifier: License :: OSI Approved :: MIT License
Classifier: Operating System :: OS Independent
Requires-Python: >=3.7
License-File: LICENSE
Requires-Dist: graphviz (==0.19.1)
Provides-Extra: docs
Requires-Dist: nbsphinx (==0.8.8) ; extra == 'docs'
Requires-Dist: sphinxcontrib-napoleon (==0.7) ; extra == 'docs'
Requires-Dist: sphinx-rtd-theme (==1.0.0) ; extra == 'docs'
Provides-Extra: test
Requires-Dist: pytest (<6,>=5.4) ; extra == 'test'
Requires-Dist: coverage (<6,>=5.2) ; extra == 'test'
